csv2sqlite3/__init__.py
csv2sqlite3/cli.py
csv2sqlite3-1.0.0.dist-info/LICENSE
csv2sqlite3-1.0.0.dist-info/METADATA
csv2sqlite3-1.0.0.dist-info/WHEEL
csv2sqlite3-1.0.0.dist-info/entry_points.txt
csv2sqlite3-1.0.0.dist-info/top_level.txt
csv2sqlite3-1.0.0.dist-info/RECORD
