Metadata-Version: 2.1
Name: csv2sqlite3
Version: 1.0.0
Summary: Simple console script for fast data analyse
Home-page: https://github.com/machineandme/csv2sqlite3
Author: Machine & Me
Author-email: ceo@machineand.me
License: UNKNOWN
Project-URL: Bug Reports, https://github.com/machineandme/csv2sqlite3/issues
Project-URL: Funding, https://www.patreon.com/machineandme
Project-URL: Source, https://github.com/machineandme/csv2sqlite3
Keywords: csv sqlite
Platform: UNKNOWN
Classifier: Development Status :: 5 - Production/Stable
Classifier: Intended Audience :: Developers
Classifier: License :: OSI Approved :: MIT License
Classifier: Programming Language :: Python :: 3
Requires-Python: >=3.*
Requires-Dist: fire (==0.2.1)
Requires-Dist: six (==1.13.0)
Requires-Dist: termcolor (==1.1.0)
